<?xml version="1.0" encoding="ISO-8859-1"?>
	<ProgramGuide>
		<Service id="1000" name="tua channel">
			<Event id="1">
				<IdName>gold.il.segno.del.potere.19742°t.</IdName>
				<StartDate>2018-02-17</StartDate>
				<StartTime>05:42:03</StartTime>
				<EndDate>2018-02-17</EndDate>
				<EndTime>06:39:58</EndTime>
				<ShortEventDescription>
					<LanguageCode>ita</LanguageCode>
					<LanguageName>Italian</LanguageName>
					<Name>GOLD  IL SEGNO DEL  POTERE 2°</Name>
					<Description>GOLD  IL SEGNO DEL  POTERE 2°</Description>
				</ShortEventDescription>
			</Event>
			<Event id="2">
				<IdName>spottc</IdName>
				<StartDate>2018-02-17</StartDate>
				<StartTime>06:39:58</StartTime>
				<EndDate>2018-02-17</EndDate>
				<EndTime>06:40:16</EndTime>
				<ShortEventDescription>
					<LanguageCode>ita</LanguageCode>
					<LanguageName>Italian</LanguageName>
					<Name>TUA CHANNEL SPOT</Name>
					<Description>SPOT TUA HANNEL</Description>
				</ShortEventDescription>
			</Event>
			<Event id="3">
				<IdName>Geracesedutaconsiliaredel5Ottobre2016(byEL)</IdName>
				<StartDate>2018-02-17</StartDate>
				<StartTime>06:40:16</StartTime>
				<EndDate>2018-02-17</EndDate>
				<EndTime>08:10:30</EndTime>
				<ShortEventDescription>
					<LanguageCode>ita</LanguageCode>
					<LanguageName>Italian</LanguageName>
					<Name>seduta consiglio gerace 5 10 106</Name>
					<Description>consiglio gerac 5.10.016</Description>
				</ShortEventDescription>
			</Event>
			<Event id="4">
				<IdName>agrisapori-621x9-8-15</IdName>
				<StartDate>2018-02-17</StartDate>
				<StartTime>08:10:30</StartTime>
				<EndDate>2018-02-17</EndDate>
				<EndTime>08:37:41</EndTime>
				<ShortEventDescription>
					<LanguageCode>ita</LanguageCode>
					<LanguageName>Italian</LanguageName>
					<Name>AGRISAPORI</Name>
					<Description>AGRISAPORI</Description>
				</ShortEventDescription>
			</Event>
			<Event id="5">
				<IdName>LaPretoraE.Fenechv.m.1419762°t.</IdName>
				<StartDate>2018-02-17</StartDate>
				<StartTime>08:37:41</StartTime>
				<EndDate>2018-02-17</EndDate>
				<EndTime>09:24:05</EndTime>
				<ShortEventDescription>
					<LanguageCode>ita</LanguageCode>
					<LanguageName>Italian</LanguageName>
					<Name>SECONDO TEMPO FENEC</Name>
					<Description>LA PRETORA</Description>
				</ShortEventDescription>
			</Event>
			<Event id="6">
				<IdName>SPOTTC4</IdName>
				<StartDate>2018-02-17</StartDate>
				<StartTime>09:24:05</StartTime>
				<EndDate>2018-02-17</EndDate>
				<EndTime>09:24:09</EndTime>
				<ShortEventDescription>
					<LanguageCode>ita</LanguageCode>
					<LanguageName>Italian</LanguageName>
					<Name>SPOTtuachanne4</Name>
					<Description>SPOTtuachanne4</Description>
				</ShortEventDescription>
			</Event>
			<Event id="7">
				<IdName>inTavola_20150205_48237</IdName>
				<StartDate>2018-02-17</StartDate>
				<StartTime>09:24:09</StartTime>
				<EndDate>2018-02-17</EndDate>
				<EndTime>09:26:08</EndTime>
				<ShortEventDescription>
					<LanguageCode>ita</LanguageCode>
					<LanguageName>Italian</LanguageName>
					<Name>Sconosciuto</Name>
					<Description>inTavola_2015 02 05</Description>
				</ShortEventDescription>
			</Event>
			<Event id="8">
				<IdName>PraiaaMarePiccolaGrandeItalia</IdName>
				<StartDate>2018-02-17</StartDate>
				<StartTime>09:26:08</StartTime>
				<EndDate>2018-02-17</EndDate>
				<EndTime>09:50:42</EndTime>
				<ShortEventDescription>
					<LanguageCode>ita</LanguageCode>
					<LanguageName>Italian</LanguageName>
					<Name>Piccola grande Italia</Name>
					<Description>PRAIA A MARE</Description>
				</ShortEventDescription>
			</Event>
			<Event id="9">
				<IdName>TG</IdName>
				<StartDate>2018-02-17</StartDate>
				<StartTime>09:50:42</StartTime>
				<EndDate>2018-02-17</EndDate>
				<EndTime>09:53:21</EndTime>
				<ShortEventDescription>
					<LanguageCode>ita</LanguageCode>
					<LanguageName>Italian</LanguageName>
					<Name>TG </Name>
					<Description>TELEGIORNALE</Description>
				</ShortEventDescription>
			</Event>
			<Event id="10">
				<IdName>Rosolinopaternosoldato_mpeg2video</IdName>
				<StartDate>2018-02-17</StartDate>
				<StartTime>09:53:21</StartTime>
				<EndDate>2018-02-17</EndDate>
				<EndTime>11:29:18</EndTime>
				<ShortEventDescription>
					<LanguageCode>ita</LanguageCode>
					<LanguageName>Italian</LanguageName>
					<Name>ROSOLINO PATERNO SOLDATO</Name>
					<Description>Rosolino paterno  soldato</Description>
				</ShortEventDescription>
			</Event>
			<Event id="11">
				<IdName>spottc</IdName>
				<StartDate>2018-02-17</StartDate>
				<StartTime>11:29:18</StartTime>
				<EndDate>2018-02-17</EndDate>
				<EndTime>11:29:37</EndTime>
				<ShortEventDescription>
					<LanguageCode>ita</LanguageCode>
					<LanguageName>Italian</LanguageName>
					<Name>TUA CHANNEL SPOT</Name>
					<Description>SPOT TUA HANNEL</Description>
				</ShortEventDescription>
			</Event>
			<Event id="12">
				<IdName>21PIXMINDrev1</IdName>
				<StartDate>2018-02-17</StartDate>
				<StartTime>11:29:37</StartTime>
				<EndDate>2018-02-17</EndDate>
				<EndTime>11:53:37</EndTime>
				<ShortEventDescription>
					<LanguageCode>ita</LanguageCode>
					<LanguageName>Italian</LanguageName>
					<Name>PIXMIND P 21</Name>
					<Description>Nuovo File</Description>
				</ShortEventDescription>
			</Event>
			<Event id="13">
				<IdName>TropeaPiccolaGrandeItalia</IdName>
				<StartDate>2018-02-17</StartDate>
				<StartTime>11:53:37</StartTime>
				<EndDate>2018-02-17</EndDate>
				<EndTime>12:20:30</EndTime>
				<ShortEventDescription>
					<LanguageCode>ita</LanguageCode>
					<LanguageName>Italian</LanguageName>
					<Name>Piccola grande Italia</Name>
					<Description>TROPEA</Description>
				</ShortEventDescription>
			</Event>
			<Event id="14">
				<IdName>Senzanomesanzaregole</IdName>
				<StartDate>2018-02-17</StartDate>
				<StartTime>12:20:30</StartTime>
				<EndDate>2018-02-17</EndDate>
				<EndTime>14:04:10</EndTime>
				<ShortEventDescription>
					<LanguageCode>ita</LanguageCode>
					<LanguageName>Italian</LanguageName>
					<Name>SENZA NOME SENZA REGOLE</Name>
					<Description>Senza nome senza regole</Description>
				</ShortEventDescription>
			</Event>
			<Event id="15">
				<IdName>SPOTTC2</IdName>
				<StartDate>2018-02-17</StartDate>
				<StartTime>14:04:10</StartTime>
				<EndDate>2018-02-17</EndDate>
				<EndTime>14:04:14</EndTime>
				<ShortEventDescription>
					<LanguageCode>ita</LanguageCode>
					<LanguageName>Italian</LanguageName>
					<Name>SPOTtuachanne2</Name>
					<Description>SPOTtuachanne2</Description>
				</ShortEventDescription>
			</Event>
			<Event id="16">
				<IdName>GeraceConsiglioComunaleStraordinariodel16Dic2015(byEL)</IdName>
				<StartDate>2018-02-17</StartDate>
				<StartTime>14:04:14</StartTime>
				<EndDate>2018-02-17</EndDate>
				<EndTime>14:54:45</EndTime>
				<ShortEventDescription>
					<LanguageCode>ita</LanguageCode>
					<LanguageName>Italian</LanguageName>
					<Name>CONSIGLIO  COMUNALE GERACE </Name>
					<Description>Consiglio  comunale gerace del 16 dic 015</Description>
				</ShortEventDescription>
			</Event>
			<Event id="17">
				<IdName>SardegnaVistadalcielo</IdName>
				<StartDate>2018-02-17</StartDate>
				<StartTime>14:54:45</StartTime>
				<EndDate>2018-02-17</EndDate>
				<EndTime>15:45:09</EndTime>
				<ShortEventDescription>
					<LanguageCode>ita</LanguageCode>
					<LanguageName>Italian</LanguageName>
					<Name>Sconosciuto</Name>
					<Description>Sardegna vista dal cielo</Description>
				</ShortEventDescription>
			</Event>
			<Event id="18">
				<IdName>UFOLeProve</IdName>
				<StartDate>2018-02-17</StartDate>
				<StartTime>15:45:09</StartTime>
				<EndDate>2018-02-17</EndDate>
				<EndTime>17:07:22</EndTime>
				<ShortEventDescription>
					<LanguageCode>ita</LanguageCode>
					<LanguageName>Italian</LanguageName>
					<Name>Sconosciuto</Name>
					<Description>Ufo le  prove</Description>
				</ShortEventDescription>
			</Event>
		</Service>
	</ProgramGuide>
